version.py
finglish/__init__.py
finglish/f2p-beginning.txt
finglish/f2p-dict.txt
finglish/f2p-ending.txt
finglish/f2p-middle.txt
finglish/f2p.py
finglish/persian-word-freq.txt
finglish/version.py
finglish-1.5.1.dist-info/LICENSE.txt
finglish-1.5.1.dist-info/METADATA
finglish-1.5.1.dist-info/WHEEL
finglish-1.5.1.dist-info/entry_points.txt
finglish-1.5.1.dist-info/top_level.txt
finglish-1.5.1.dist-info/RECORD
