Metadata-Version: 2.1
Name: finglish
Version: 1.5.1
Summary: Finglish-to-Persian converter.
Home-page: https://github.com/elektito/finglish
Author: Mostafa Razavi
Author-email: mostafa@sepent.com
License: MIT
Download-URL: https://github.com/elektito/finglish/tarball/1.5.1
Keywords: persian,finglish
Platform: UNKNOWN
Classifier: Programming Language :: Python :: 3
